huaweicloudsdkdds/__init__.py
huaweicloudsdkdds/v3/__init__.py
huaweicloudsdkdds/v3/dds_async_client.py
huaweicloudsdkdds/v3/dds_client.py
huaweicloudsdkdds/v3/model/__init__.py
huaweicloudsdkdds/v3/model/add_readonly_node_request.py
huaweicloudsdkdds/v3/model/add_readonly_node_request_body.py
huaweicloudsdkdds/v3/model/add_readonly_node_response.py
huaweicloudsdkdds/v3/model/add_sharding_node_request.py
huaweicloudsdkdds/v3/model/add_sharding_node_response.py
huaweicloudsdkdds/v3/model/add_sharding_node_volume_option.py
huaweicloudsdkdds/v3/model/api_version.py
huaweicloudsdkdds/v3/model/applicable_instances_info.py
huaweicloudsdkdds/v3/model/apply_configuration_request_body.py
huaweicloudsdkdds/v3/model/apply_history_info.py
huaweicloudsdkdds/v3/model/attach_eip_request.py
huaweicloudsdkdds/v3/model/attach_eip_request_body.py
huaweicloudsdkdds/v3/model/attach_eip_response.py
huaweicloudsdkdds/v3/model/attach_internal_ip_request.py
huaweicloudsdkdds/v3/model/attach_internal_ip_request_body.py
huaweicloudsdkdds/v3/model/attach_internal_ip_response.py
huaweicloudsdkdds/v3/model/az2_migrate.py
huaweicloudsdkdds/v3/model/backup_database.py
huaweicloudsdkdds/v3/model/backup_for_list.py
huaweicloudsdkdds/v3/model/backup_policy.py
huaweicloudsdkdds/v3/model/backup_policy_item.py
huaweicloudsdkdds/v3/model/backup_strategy.py
huaweicloudsdkdds/v3/model/backup_strategy_for_item_response.py
huaweicloudsdkdds/v3/model/balancer_active_window.py
huaweicloudsdkdds/v3/model/batch_delete_backup_request.py
huaweicloudsdkdds/v3/model/batch_delete_backup_request_body.py
huaweicloudsdkdds/v3/model/batch_delete_backup_response.py
huaweicloudsdkdds/v3/model/batch_operate_instance_tag_request_body.py
huaweicloudsdkdds/v3/model/batch_tag_action_request.py
huaweicloudsdkdds/v3/model/batch_tag_action_response.py
huaweicloudsdkdds/v3/model/batch_upgrade_database_version_request.py
huaweicloudsdkdds/v3/model/batch_upgrade_database_version_request_body.py
huaweicloudsdkdds-3.1.184.dist-info/METADATA
huaweicloudsdkdds-3.1.184.dist-info/WHEEL
huaweicloudsdkdds-3.1.184.dist-info/licenses/LICENSE
huaweicloudsdkdds-3.1.184.dist-info/RECORD
